fids/__init__.py
fids/_version.py
fids/fids.py
fids/config/bids.json
fids/config/derivatives.json
fids-0.1.0.dist-info/METADATA
fids-0.1.0.dist-info/WHEEL
fids-0.1.0.dist-info/licenses/LICENSE
fids-0.1.0.dist-info/RECORD
